{
    "type": "minecraft:crafting_shaped",
   
    "pattern":
    [
        "GF ",
        "IHI",
        "   "
    ],
   
    "key":
    {
        "G":
        {
            "item": "minecraft:glass_pane"
        },
        "F":
        {
            "item": "am:flux_ore"
        },
        "I":
        {
            "item": "minecraft:iron_ingot"
        },
        "H":
        {
            "item": "minecraft:furnace"
        }
    },
   
    "result":
    {
        "item": "am:flux_generator_block",
        "count": 1
    }
}