{
    "variants": 
    {
        "burning=false,facing=north": { "model": "advmod:flux_crafter_block" },
        "burning=false,facing=east": { "model": "advmod:flux_crafter_block", "y": 90 },
        "burning=false,facing=south": { "model": "advmod:flux_crafter_block", "y": 180 },
        "burning=false,facing=west": { "model": "advmod:flux_crafter_block", "y": 270},
        "burning=true,facing=north": { "model": "advmod:flux_crafter_block_on" },
        "burning=true,facing=east": { "model": "advmod:flux_crafter_block_on", "y": 90 },
        "burning=true,facing=south": { "model": "advmod:flux_crafter_block_on", "y": 180 },
        "burning=true,facing=west": { "model": "advmod:flux_crafter_block_on", "y": 270}
    }
}